{
    "competences": [
        {
            "label": "Angular",
            "descriptionFr": "Framework frontend TypeScript",
            "descriptionEn": "Framework frontend TypeScript",
            "type": "framework",
            "experiences": [
                "Orange",
                "personal"
            ],
            "lvl": 70
        },
        {
            "label": "VueJS",
            "descriptionFr": "Framework frontend JavaScript",
            "descriptionEn": "Framework frontend JavaScript",
            "type": "framework",
            "experiences": [
                "Orange",
                "personal"
            ],
            "lvl": 50
        },
        {
            "label": "Java spring",
            "descriptionFr": "Framework backend java",
            "descriptionEn": "Framework backend java",
            "type": "framework",
            "experiences": [
                "Orange"
            ],
            "lvl": 70
        },
        {
            "label": "JQuery",
            "descriptionFr": "Framework frontend JavaScript",
            "descriptionEn": "Framework frontend JavaScript",
            "type": "framework",
            "experiences": [
                "3IL",
                "personal"
            ],
            "lvl": 80
        },
        {
            "label": "Swagger",
            "descriptionFr": "API designer",
            "descriptionEn": "API designer",
            "type": "framework",
            "experiences": [
                "personal"
            ],
            "lvl": 80
        },
        {
            "label": "Django",
            "descriptionFr": "Framework backend python",
            "descriptionEn": "Framework backend python",
            "type": "framework",
            "experiences": [
                "Association \"Sème tes graines\""
            ],
            "lvl": 50
        },
        {
            "label": "JavaScript",
            "descriptionFr": "Langage de programmation JavaScript",
            "descriptionEn": "Programming language JavaScript",
            "type": "language",
            "experiences": [
                "Orange",
                "personal"
            ],
            "lvl": 80
        },
        {
            "label": "TypeScript",
            "descriptionFr": "Langage de programmation TypeScript",
            "descriptionEn": "Programming language TypeScript",
            "type": "language",
            "experiences": [
                "Orange",
                "personal"
            ],
            "lvl": 70
        },
        {
            "label": "Kotlin",
            "descriptionFr": "Langage de programmation Kotlin",
            "descriptionEn": "Programming language Kotlin",
            "type": "language",
            "experiences": [
                "Orange",
                "personal"
            ],
            "lvl": 60
        },
        {
            "label": "Java",
            "descriptionFr": "Langage de programmation Java",
            "descriptionEn": "Programming language Java",
            "type": "language",
            "experiences": [
                "3IL",
                "Orange",
                "personal"
            ],
            "lvl": 70
        },
        {
            "label": "PHP",
            "descriptionFr": "Langage de programmation PHP",
            "descriptionEn": "Programming language PHP",
            "type": "language",
            "experiences": [
                "BTS Beaupeyrat",
                "3IL",
                "personal"
            ],
            "lvl": 70
        },
        {
            "label": "ANTLR",
            "descriptionFr": "Framework de construction de compilateurs",
            "descriptionEn": "Framework for compiler construction",
            "type": "language",
            "experiences": [
                "Orange"
            ],
            "lvl": 60
        },
        {
            "label": "C++",
            "descriptionFr": "Langage de programmation C++",
            "descriptionEn": "Programming language C++",
            "type": "language",
            "experiences": [
                "3IL",
                "personal"
            ],
            "lvl": 50
        },
        {
            "label": "Python",
            "descriptionFr": "Langage de programmation Python",
            "descriptionEn": "Programming language Python",
            "type": "language",
            "experiences": [
                "Association \"Sème tes graines\"",
                "personal"
            ],
            "lvl": 70
        },
        {
            "label": "MySQL",
            "descriptionFr": "Base de données relationnelles",
            "descriptionEn": "Relational database",
            "type": "db",
            "experiences": [
                "BTS Beaupeyrat",
                "3IL",
                "Orange",
                "personal"
            ],
            "lvl": 80
        },
        {
            "label": "PostgreSQL",
            "descriptionFr": "Base de données relationnelles",
            "descriptionEn": "Relational database",
            "type": "db",
            "experiences": [
                "personal"
            ],
            "lvl": 70
        },
        {
            "label": "SQLite",
            "descriptionFr": "Base de données relationnelles",
            "descriptionEn": "Relational database",
            "type": "db",
            "experiences": [
                "BTS Beaupeyrat",
                "personal"
            ],
            "lvl": 70
        },
        {
            "label": "MongoDB",
            "descriptionFr": "Base de données orientée documents",
            "descriptionEn": "Document database",
            "type": "db",
            "experiences": [
                "Orange",
                "personal"
            ],
            "lvl": 70
        },
        {
            "label": "Neo4J",
            "descriptionFr": "Base de données orientée graphe",
            "descriptionEn": "Graph database",
            "type": "db",
            "experiences": [
                "Orange",
                "personal"
            ],
            "lvl": 70
        },
        {
            "label": "Redis",
            "descriptionFr": "Base de données clé-valeur",
            "descriptionEn": "Key-value database",
            "type": "db",
            "experiences": [
                "personal"
            ],
            "lvl": 60
        },
        {
            "label": "Apache Kafka",
            "descriptionFr": "File de messages asynchrones",
            "descriptionEn": "Asynchronous message queue",
            "type": "bigData",
            "experiences": [
                "Orange"
            ],
            "lvl": 60
        },
        {
            "label": "Apache Spark",
            "descriptionFr": "Framework de calculs distribués",
            "descriptionEn": "Distributed framework",
            "type": "bigData",
            "experiences": [
                "Orange",
                "personal"
            ],
            "lvl": 30
        },
        {
            "label": "Apache Ni-Fi",
            "descriptionFr": "Framework de gestion de flux",
            "descriptionEn": "Flow management framework",
            "type": "bigData",
            "experiences": [
                "Orange"
            ],
            "lvl": 30
        },
        {
            "label": "Apache Hadoop HDFS",
            "descriptionFr": "Système de fichiers distribué",
            "descriptionEn": "Hight level distributed file system",
            "type": "bigData",
            "experiences": [
                "Orange"
            ],
            "lvl": 40
        },
        {
            "label": "Linux",
            "descriptionFr": "Système d'exploitation Linux",
            "descriptionEn": "Operating system Linux",
            "type": "os",
            "experiences": [
                "BTS Beaupeyrat",
                "3IL",
                "Orange",
                "personal"
            ],
            "lvl": 80
        },
        {
            "label": "Windows",
            "descriptionFr": "Système d'exploitation Windows",
            "descriptionEn": "Operating system Windows",
            "type": "os",
            "experiences": [
                "BTS Beaupeyrat",
                "3IL",
                "Orange",
                "personal"
            ],
            "lvl": 60
        },
        {
            "label": "Postfix",
            "descriptionFr": "Serveur (mail) SMTP",
            "descriptionEn": "SMTP (mail) server",
            "type": "network",
            "experiences": [
                "personal"
            ],
            "lvl": 50
        },
        {
            "label": "Apache 2",
            "descriptionFr": "Serveur HTTP",
            "descriptionEn": "HTTP server",
            "type": "network",
            "experiences": [
                "BTS Beaupeyrat",
                "3IL",
                "personal"
            ],
            "lvl": 60
        },
        {
            "label": "NGINX",
            "descriptionFr": "Serveur HTTP / Reverse proxy",
            "descriptionEn": "HTTP server / Reverse proxy",
            "type": "network",
            "experiences": [
                "Orange",
                "personal"
            ],
            "lvl": 80
        },
        {
            "label": "Bind 9",
            "descriptionFr": "DNS",
            "descriptionEn": "DNS",
            "type": "network",
            "experiences": [
                "personal"
            ],
            "lvl": 80
        },
        {
            "label": "Squid",
            "descriptionFr": "Proxy",
            "descriptionEn": "Proxy",
            "type": "network",
            "experiences": [
                "personal"
            ],
            "lvl": 50
        },
        {
            "label": "Docker",
            "descriptionFr": "Gestionnaire de conteneurs",
            "descriptionEn": "Container manager",
            "type": "tool",
            "experiences": [
                "BTS Beaupeyrat",
                "3IL",
                "Orange",
                "personal"
            ],
            "lvl": 85
        },
        {
            "label": "Kubernetes",
            "descriptionFr": "Orchestrateur d'infrastructures conteneurisées",
            "descriptionEn": "Container infrastructure orchestrator",
            "type": "tool",
            "experiences": [
                "Orange"
            ],
            "lvl": 60
        },
        {
            "label": "Visual Studio Code",
            "descriptionFr": "IDE JavaScript",
            "descriptionEn": "IDE JavaScript",
            "type": "tool",
            "experiences": [
                "BTS Beaupeyrat",
                "3IL",
                "Orange",
                "personal"
            ],
            "lvl": 80
        },
        {
            "label": "Intellij",
            "descriptionFr": "IDE Java / Kotlin",
            "descriptionEn": "IDE Java / Kotlin",
            "type": "tool",
            "experiences": [
                "3IL",
                "Orange",
                "personal"
            ],
            "lvl": 75
        },
        {
            "label": "CloudFoundry",
            "descriptionFr": "Plateforme PaaS",
            "descriptionEn": "PaaS platform",
            "type": "tool",
            "experiences": [
                "Orange"
            ],
            "lvl": 80
        },
        {
            "label": "GIT",
            "descriptionFr": "Logiciel de gestion de versions",
            "descriptionEn": "Ddistributed version control system",
            "type": "tool",
            "experiences": [
                "BTS Beaupeyrat",
                "3IL",
                "Orange",
                "personal"
            ],
            "lvl": 60
        },
        {
            "label": "Gitlab",
            "descriptionFr": "Implémentation de GIT",
            "descriptionEn": "GIT implementation",
            "type": "tool",
            "experiences": [
                "Orange"
            ],
            "lvl": 60
        },
        {
            "label": "GitlabCI",
            "descriptionFr": "Gestion de pipelines de déploiement continu",
            "descriptionEn": "Continuous deployment pipeline management",
            "type": "tool",
            "experiences": [
                "Orange"
            ],
            "lvl": 70
        },
        {
            "label": "Scrum",
            "descriptionFr": "Méthode de management dite agile",
            "descriptionEn": "Agile management method",
            "type": "management",
            "experiences": [
                "Orange"
            ],
            "lvl": 70
        }
    ]
}